Workbook

Sheet Resumen
A1: Costo mensual estimado · 500 personas en GlowApp sobre Railway
A2: Escenario BASE: 500 personas activas, 1,5 escaneos/mes cada una, chat moderado. Cifras en USD, mes calendario, impuestos no incluidos.
A3: Métrica | B3: BAJO | C3: BASE | D3: ALTO | E3: Nota
A4: Personas activas / mes | B4: ='Costos IA'!C15 -> 300 | C4: ='Costos IA'!D15 -> 500 | D4: ='Costos IA'!E15 -> 500 | E4: Personas objetivo × % activos.
A5: Escaneos faciales / mes | B5: ='Costos IA'!C4 -> 300 | C5: ='Costos IA'!D4 -> 750 | D5: ='Costos IA'!E4 -> 1250
A6: Costo de IA y APIs | B6: ='Costos IA'!C12 -> 319.44 | C6: ='Costos IA'!D12 -> 803.77313 | D6: ='Costos IA'!E12 -> 1348.2594 | E6: YouCam + Gemini + DeepSeek.
A7: Infraestructura Railway | B7: ='Infra Railway'!$H$15 -> 71.45 | C7: ='Infra Railway'!$H$15 -> 71.45 | D7: ='Infra Railway'!$H$15 -> 71.45 | E7: Casi fija; no escala con usuarios.
A8: TOTAL MENSUAL | B8: =B6+B7 -> 390.89 | C8: =C6+C7 -> 875.22312 | D8: =D6+D7 -> 1419.7094
A9: Costo por persona activa | B9: =B8/B4 -> 1.3029667 | C9: =C8/C4 -> 1.7504462 | D9: =D8/D4 -> 2.8394188
A10: Costo por persona (500) | B10: =B8/Supuestos!$C$4 -> 0.78178 | C10: =C8/Supuestos!$C$4 -> 1.7504462 | D10: =D8/Supuestos!$C$4 -> 2.8394188 | E10: Referencia del caso solicitado.
A11: % del costo que es IA | B11: =B6/B8 -> 0.817212 | C11: =C6/C8 -> 0.91836367 | D11: =D6/D8 -> 0.9496728
A12: % del costo que es Railway | B12: =B7/B8 -> 0.182788 | C12: =C7/C8 -> 0.081636326 | D12: =D7/D8 -> 0.050327202
A13: YouCam (dentro de IA) | B13: ='Costos IA'!C6 -> 316.8 | C13: ='Costos IA'!D6 -> 792 | D13: ='Costos IA'!E6 -> 1320 | E13: Un solo proveedor concentra el gasto.
A14: Unidades YouCam / mes | B14: ='Costos IA'!C5 -> 6600 | C14: ='Costos IA'!D5 -> 16500 | D14: ='Costos IA'!E5 -> 27500
A15: Costo IA por escaneo | B15: ='Costos IA'!C13 -> 1.0648 | C15: ='Costos IA'!D13 -> 1.0716975 | D15: ='Costos IA'!E13 -> 1.0786075 | E15: Margen unitario.
A36: Lectura rápida
A37: 1) El costo lo manda YouCam, no Railway: un escaneo HD de 16 acciones consume 22 unidades (~USD 1,06). 2) La infraestructura es casi fija (~USD 70/mes) porque los contenedores están encendidos aunque no haya tráfico. 3) El documento GIA-14-I estima USD 0,04 por persona/mes (~USD 20 para 500): eso no cubre ni la infraestructura ni un solo escaneo.

Sheet Resumen COP
A1: Costo mensual en pesos colombianos (COP)
A2: Conversión a la TRM vigente del 24–26 de octubre de 2026: $3.158,43 COP/USD (Superfinanciera). Los proveedores facturan en USD; la TRM cambia la lectura local y el riesgo cambiario, no la factura.
A4: Métrica | B4: BAJO | C4: BASE | D4: ALTO | E4: Nota
A5: TRM usada (COP por USD) | B5: =Supuestos!$C$33 -> 3158.43 | C5: =Supuestos!$C$33 -> 3158.43 | D5: =Supuestos!$C$33 -> 3158.43 | E5: Editable en Supuestos (fila 33).
A6: TOTAL MENSUAL (COP) | B6: =Resumen!B8*B$5 -> 1234598.7 | C6: =Resumen!C8*C$5 -> 2764331 | D6: =Resumen!D8*D$5 -> 4484052.7 | E6: Costo total del mes.
A7: IA y APIs (COP) | B7: =Resumen!B6*B$5 -> 1008928.9 | C7: =Resumen!C6*C$5 -> 2538661.2 | D7: =Resumen!D6*D$5 -> 4258382.9 | E7: 92 % del total en BASE.
A8: Railway (COP) | B8: =Resumen!B7*B$5 -> 225669.82 | C8: =Resumen!C7*C$5 -> 225669.82 | D8: =Resumen!D7*D$5 -> 225669.82 | E8: Casi fijo.
A9: YouCam (COP) | B9: =Resumen!B13*B$5 -> 1000590.6 | C9: =Resumen!C13*C$5 -> 2501476.6 | D9: =Resumen!D13*D$5 -> 4169127.6 | E9: Dentro de IA.
A10: Costo por persona activa (COP) | B10: =Resumen!B9*B$5 -> 4115.329 | C10: =Resumen!C9*C$5 -> 5528.6619 | D10: =Resumen!D9*D$5 -> 8968.1054 | E10: Mensual.
A11: Costo por persona / 500 (COP) | B11: =Resumen!B10*B$5 -> 2469.1974 | C11: =Resumen!C10*C$5 -> 5528.6619 | D11: =Resumen!D10*D$5 -> 8968.1054 | E11: Mensual.
A12: Costo por escaneo (COP) | B12: =Resumen!B15*B$5 -> 3363.0963 | C12: =Resumen!C15*C$5 -> 3384.8815 | D12: =Resumen!D15*D$5 -> 3406.7063 | E12: Variable dominante.
A13: Costo por escaneo (USD) | B13: =Resumen!B15 -> 1.0648 | C13: =Resumen!C15 -> 1.0716975 | D13: =Resumen!D15 -> 1.0786075 | E13: Referencia.
A16: Sensibilidad a la TRM (escenario BASE)
A17: Escenario de TRM | B17: TRM (COP/USD) | C17: Total BASE (COP) | D17: Variación
A18: TRM 10 % más baja | B18: =$C$5*0.9 -> 2842.587 | C18: =Resumen!$C$8*B18 -> 2487897.9 | D18: =C18/$C$19-1 -> -0.1
A19: TRM vigente | B19: =$C$5*1 -> 3158.43 | C19: =Resumen!$C$8*B19 -> 2764331 | D19: =C19/$C$19-1 -> 0
A20: TRM 10 % más alta | B20: =$C$5*1.1 -> 3474.273 | C20: =Resumen!$C$8*B20 -> 3040764.1 | D20: =C20/$C$19-1 -> 0.1
A23: La TRM no altera el costo en USD: si el ingreso es en pesos y la factura en dólares, una devaluación del 10 % sube el costo en COP 10 % con el mismo consumo. El punto medio de la banda (USD 875) equivale a ≈ $2,76 millones COP/mes.

Sheet Supuestos
A1: Supuestos de la simulación · 500 personas · GlowApp en Railway
A2: Celdas amarillas = entradas editables. Las columnas BAJO / BASE / ALTO son tres perfiles de uso. Todo lo demás del libro se recalcula a partir de aquí.
A3: Parámetro | B3: Unidad | C3: BAJO | D3: BASE | E3: ALTO | F3: Fuente / evidencia
A4: Personas objetivo | B4: usuarios | C4: 500 | D4: 500 | E4: 500 | F4: Caso solicitado: 500 personas.
A5: % de esas personas activas en el mes | B5: % | C5: 0.6 | D5: 1 | E5: 1 | F5: Supuesto de producto; no hay telemetría en el repo.
A6: Escaneos faciales por persona activa / mes | B6: escaneos | C6: 1 | D6: 1.5 | E6: 2.5 | F6: Protocolo Día 1 + re-escaneo Día 15/30 (GIA-13-N).
A7: Acciones HD solicitadas por escaneo | B7: acciones | C7: 16 | D7: 16 | E7: 16 | F7: backend/src/services/biometric/youcam.client.js: SKIN_ANALYSIS_ACTIONS (16).
A8: Unidades YouCam consumidas por escaneo | B8: unidades | C8: 22 | D8: 22 | E8: 22 | F8: Tabla oficial: 13–16 concerns HD = 22 unidades.
A9: Precio por unidad YouCam (suscripción) | B9: USD/unidad | C9: 0.048 | D9: 0.048 | E9: 0.048 | F9: Plan suscripción 500+ unidades. PAYG = 0.055.
A10: Mensajes al chat de IA por persona activa / mes | B10: mensajes | C10: 4 | D10: 12 | E10: 30 | F10: Supuesto de engagement; el chat usa DeepSeek con RAG topK=5.
A11: Tokens de entrada por mensaje de chat | B11: tokens | C11: 4000 | D11: 4000 | E11: 4000 | F11: RAG topK=5 + catálogo de servicios cacheado + historial.
A12: Tokens de salida por mensaje de chat | B12: tokens | C12: 450 | D12: 450 | E12: 450 | F12: Respuesta conversacional típica.
A13: Tokens de entrada · Gemini manos (imagen) | B13: tokens | C13: 1100 | D13: 1100 | E13: 1100 | F13: Imagen normalizada + prompt corto (gemini.client.js, maxOutputTokens 256).
A14: Tokens de salida · Gemini manos | B14: tokens | C14: 200 | D14: 200 | E14: 200 | F14: Salida JSON corta.
A15: Tokens de entrada · DeepSeek recomendación | B15: tokens | C15: 450 | D15: 450 | E15: 450 | F15: RECOMMENDATION_PROMPT (prompts.js).
... A33: TRM COP/USD | B33: COP por USD | C33: 3158.43 | D33: 3158.43 | E33: 3158.43 | F33: TRM vigente 24–26 oct 2026 (Superfinanciera). Editable.

Sheet Costos IA
A1: Costos de IA y APIs externas
A2: YouCam se cobra por unidad (22 unidades por escaneo HD de 16 acciones). Gemini y DeepSeek se cobran por token. Ver hoja Supuestos para editar.
A3: Concepto | B3: Detalle | C3: BAJO | D3: BASE | E3: ALTO | F3: Nota
A4: Escaneos faciales / mes | B4: personas activas × escaneos | C4: =Supuestos!C$4*Supuestos!C$5*Supuestos!C$6 -> 300 | D4: =Supuestos!D$4*Supuestos!D$5*Supuestos!D$6 -> 750 | E4: =Supuestos!E$4*Supuestos!E$5*Supuestos!E$6 -> 1250 | F4: Volumen que dispara el costo.
A5: Unidades YouCam / mes | B5: escaneos × 22 unidades | C5: =C4*Supuestos!C$8 -> 6600 | D5: =D4*Supuestos!D$8 -> 16500 | E5: =E4*Supuestos!E$8 -> 27500 | F5: 13–16 concerns en HD.
A6: YouCam · análisis facial (16 HD) | B6: unidades × precio unidad | C6: =C5*Supuestos!C$9 -> 316.8 | D6: =D5*Supuestos!D$9 -> 792 | E6: =E5*Supuestos!E$9 -> 1320 | F6: Rubro dominante.
A7: Gemini · diagnóstico de manos | B7: escaneos × (in·p_in + out·p_out) | C7: =C4*(Supuestos!C$13*Supuestos!C$19+Supuestos!C$14*Supuestos!C$20)/1000000 -> 0.08625 | D7: =D4*(Supuestos!D$13*Supuestos!D$19+Supuestos!D$14*Supuestos!D$20)/1000000 -> 0.215625 | E7: =E4*(Supuestos!E$13*Supuestos!E$19+Supuestos!E$14*Supuestos!E$20)/1000000 -> 0.359375 | F7: Visión, salida corta.
A8: DeepSeek · recomendación | B8: escaneos × tokens | C8: =C4*(Supuestos!C$15*Supuestos!C$21+Supuestos!C$16*Supuestos!C$22)/1000000 -> 0.2925 | D8: =D4*(Supuestos!D$15*Supuestos!D$21+Supuestos!D$16*Supuestos!D$22)/1000000 -> 0.73125 | E8: =E4*(Supuestos!E$15*Supuestos!E$21+Supuestos!E$16*Supuestos!E$22)/1000000 -> 1.21875 | F8: Rutina AM/PM.
A9: DeepSeek · matching de tonos VTO | B9: escaneos × tokens | C9: =C4*(Supuestos!C$17*Supuestos!C$21+Supuestos!C$18*Supuestos!C$22)/1000000 -> 0.117 | D9: =D4*(Supuestos!D$17*Supuestos!D$21+Supuestos!D$18*Supuestos!D$22)/1000000 -> 0.2925 | E9: =E4*(Supuestos!E$17*Supuestos!E$21+Supuestos!E$18*Supuestos!E$22)/1000000 -> 0.4875 | F9: Paleta por subtono.
A10: DeepSeek · chat asistente (RAG) | B10: mensajes × tokens | C10: =Supuestos!C$4*Supuestos!C$5*Supuestos!C$10*(Supuestos!C$11*Supuestos!C$21+Supuestos!C$12*Supuestos!C$22)/1000000 -> 2.088 | D10: =Supuestos!D$4*Supuestos!D$5*Supuestos!D$10*(Supuestos!D$11*Supuestos!D$21+Supuestos!D$12*Supuestos!D$22)/1000000 -> 10.44 | E10: =Supuestos!E$4*Supuestos!E$5*Supuestos!E$10*(Supuestos!E$11*Supuestos!E$21+Supuestos!E$12*Supuestos!E$22)/1000000 -> 26.1 | F10: Crece con engagement.
A11: Gemini · análisis de forma facial | B11: llamadas × tokens | C11: =Supuestos!C$4*Supuestos!C$5*Supuestos!C$23*(Supuestos!C$24*Supuestos!C$19+Supuestos!C$25*Supuestos!C$20)/1000000 -> 0.05625 | D11: =Supuestos!D$4*Supuestos!D$5*Supuestos!D$23*(Supuestos!D$24*Supuestos!D$19+Supuestos!D$25*Supuestos!D$20)/1000000 -> 0.09375 | E11: =Supuestos!E$4*Supuestos!E$5*Supuestos!E$23*(Supuestos!E$24*Supuestos!E$19+Supuestos!E$25*Supuestos!E$20)/1000000 -> 0.09375 | F11: Módulo de diseños.
A12: TOTAL IA / mes | B12: suma | C12: =SUM(C6:C11) -> 319.44 | D12: =SUM(D6:D11) -> 803.77313 | E12: =SUM(E6:E11) -> 1348.2594 | F12: Solo APIs de IA.
A13: Costo IA por escaneo | B13: total ÷ escaneos | C13: =C12/C4 -> 1.0648 | D13: =D12/D4 -> 1.0716975 | E13: =E12/E4 -> 1.0786075 | F13: Margen unitario.
A14: Costo IA por persona activa | B14: total ÷ activos | C14: =C12/(Supuestos!C$4*Supuestos!C$5) -> 1.0648 | D14: =D12/(Supuestos!D$4*Supuestos!D$5) -> 1.6075462 | E14: =E12/(Supuestos!E$4*Supuestos!E$5) -> 2.6965188
A15: Personas activas / mes | B15: personas × % activos | C15: =Supuestos!C$4*Supuestos!C$5 -> 300 | D15: =Supuestos!D$4*Supuestos!D$5 -> 500 | E15: =Supuestos!E$4*Supuestos!E$5 -> 500

Sheet Infra Railway
A1: Infraestructura Railway · consumo mensual estimado
A2: Railway cobra por segundo: CPU, RAM y volumen. Los valores de vCPU/RAM son promedios mensuales supuestos (no hay métricas históricas en el repo). Ajuste la columna B/D/F con las métricas reales del dashboard.
A3: Servicio | B3: vCPU prom. | C3: Costo CPU | D3: RAM GB prom. | E3: Costo RAM | F3: Volumen GB | G3: Costo volumen | H3: Subtotal | I3: Nota
A4: API Node/Express (backend) | B4: 0.25 | C4: =B4*Supuestos!$C$28 -> 5 | D4: 0.6 | E4: =D4*Supuestos!$C$29 -> 6 | F4: 0 | G4: =F4*Supuestos!$C$30 -> 0 | H4: =C4+E4+G4 -> 11 | I4: Dockerfile.prod, Sequelize + sharp.
A5: ai-worker FastAPI (Pillow/numpy) | B5: 0.1 | C5: =B5*Supuestos!$C$28 -> 2 | D5: 0.3 | E5: =D5*Supuestos!$C$29 -> 3 | F5: 0 | G5: =F5*Supuestos!$C$30 -> 0 | H5: =C5+E5+G5 -> 5 | I5: Procesa imágenes en CPU, sin GPU.
A6: PostgreSQL 16 + pgvector | B6: 0.25 | C6: =B6*Supuestos!$C$28 -> 5 | D6: 1 | E6: =D6*Supuestos!$C$29 -> 10 | F6: 12 | G6: =F6*Supuestos!$C$30 -> 1.8 | H6: =C6+E6+G6 -> 16.8 | I6: BD + embeddings + índices HNSW.
A7: Redis 7 | B7: 0.05 | C7: =B7*Supuestos!$C$28 -> 1 | D7: 0.25 | E7: =D7*Supuestos!$C$29 -> 2.5 | F7: 0 | G7: =F7*Supuestos!$C$30 -> 0 | H7: =C7+E7+G7 -> 3.5 | I7: Caché y colas.
A8: Frontend Flutter Web (nginx) | B8: 0.05 | C8: =B8*Supuestos!$C$28 -> 1 | D8: 0.2 | E8: =D8*Supuestos!$C$29 -> 2 | F8: 0 | G8: =F8*Supuestos!$C$30 -> 0 | H8: =C8+E8+G8 -> 3 | I8: Build estático servido por nginx.
A9: Admin dashboard | B9: 0.05 | C9: =B9*Supuestos!$C$28 -> 1 | D9: 0.2 | E9: =D9*Supuestos!$C$29 -> 2 | F9: 0 | G9: =F9*Supuestos!$C$30 -> 0 | H9: =C9+E9+G9 -> 3 | I9: Uso interno esporádico.
A10: TOTAL SERVICIOS | H10: =SUM(H4:H9) -> 42.3
A11: Egress (API + estáticos, 40 GB/mes) | H11: =40*Supuestos!$C$31 -> 2
A12: SUBTOTAL PRODUCCIÓN | H12: =H10+H11 -> 44.3
A13: Staging (clon de producción) | H13: =H12*Supuestos!$C$26 -> 22.15
A14: Varios (dominio, R2, Sentry) | H14: =Supuestos!$C$27 -> 5
A15: TOTAL INFRAESTRUCTURA / mes | H15: =H12+H13+H14 -> 71.45
A17: Supuestos de tamaño por servicio
A18: Los promedios de vCPU/RAM son estimaciones de dimensionamiento para 500 usuarios activos al mes, no lecturas del dashboard de Railway. Con 500 usuarios el consumo es mayormente línea base (contenedores encendidos), por eso el costo de infraestructura es casi fijo y no escala 1:1 con las personas.

Sheet Sensibilidad
A1: Sensibilidad · qué mueve el costo
A2: Cada tabla aísla una palanca manteniendo el resto en el escenario BASE.
A3: A. Unidades YouCam por escaneo (precio 0,048/unidad, 750 escaneos/mes)
A4: Configuración | B4: Unidades | C4: USD / escaneo | D4: USD / mes (solo YouCam) | E4: Ahorro vs actual
A5: 1–4 concerns (SD) | B5: 9 | C5: =B5*Supuestos!$C$9 -> 0.432 | D5: =C5*'Costos IA'!$D$4 -> 324 | E5: =1-D5/$D$9 -> 0.59090909
A6: 5–8 concerns (SD) | B6: 12 | C6: =B6*Supuestos!$C$9 -> 0.576 | D6: =C6*'Costos IA'!$D$4 -> 432 | E6: =1-D6/$D$9 -> 0.45454545
A7: 9–12 concerns (SD) | B7: 14 | C7: =B7*Supuestos!$C$9 -> 0.672 | D7: =C7*'Costos IA'!$D$4 -> 504 | E7: =1-D7/$D$9 -> 0.36363636
A8: 13–16 concerns (SD) | B8: 16 | C8: =B8*Supuestos!$C$9 -> 0.768 | D8: =C8*'Costos IA'!$D$4 -> 576 | E8: =1-D8/$D$9 -> 0.27272727
A9: 13–16 concerns (HD) — actual | B9: 22 | C9: =B9*Supuestos!$C$9 -> 1.056 | D9: =C9*'Costos IA'!$D$4 -> 792 | E9: =1-D9/$D$9 -> 0
A10: 16 acciones HD + reintentos | B10: 30 | C10: =B10*Supuestos!$C$9 -> 1.44 | D10: =C10*'Costos IA'!$D$4 -> 1080 | E10: =1-D10/$D$9 -> -0.36363636
A12: B. Escaneos por mes (resto en BASE)
A13: Escaneos / mes | B13: Costo variable IA | C13: Chat + forma facial | D13: Infraestructura | E13: TOTAL
A14: 250 | B14: =A14*('Costos IA'!$D$6+'Costos IA'!$D$7+'Costos IA'!$D$8+'Costos IA'!$D$9)/'Costos IA'!$D$4 -> 264.41312 | C14: ='Costos IA'!$D$10+'Costos IA'!$D$11 -> 10.53375 | D14: ='Infra Railway'!$H$15 -> 71.45 | E14: =B14+C14+D14 -> 346.39688
A15: 500 | B15: =A15*('Costos IA'!$D$6+'Costos IA'!$D$7+'Costos IA'!$D$8+'Costos IA'!$D$9)/'Costos IA'!$D$4 -> 528.82625 | C15: ='Costos IA'!$D$10+'Costos IA'!$D$11 -> 10.53375 | D15: ='Infra Railway'!$H$15 -> 71.45 | E15: =B15+C15+D15 -> 610.81
A16: 750 | B16: =A16*('Costos IA'!$D$6+'Costos IA'!$D$7+'Costos IA'!$D$8+'Costos IA'!$D$9)/'Costos IA'!$D$4 -> 793.23937 | C16: ='Costos IA'!$D$10+'Costos IA'!$D$11 -> 10.53375 | D16: ='Infra Railway'!$H$15 -> 71.45 | E16: =B16+C16+D16 -> 875.22312
A17: 1000 | B17: =A17*('Costos IA'!$D$6+'Costos IA'!$D$7+'Costos IA'!$D$8+'Costos IA'!$D$9)/'Costos IA'!$D$4 -> 1057.6525 | C17: ='Costos IA'!$D$10+'Costos IA'!$D$11 -> 10.53375 | D17: ='Infra Railway'!$H$15 -> 71.45 | E17: =B17+C17+D17 -> 1139.6363
A18: 1500 | B18: =A18*('Costos IA'!$D$6+'Costos IA'!$D$7+'Costos IA'!$D$8+'Costos IA'!$D$9)/'Costos IA'!$D$4 -> 1586.4787 | C18: ='Costos IA'!$D$10+'Costos IA'!$D$11 -> 10.53375 | D18: ='Infra Railway'!$H$15 -> 71.45 | E18: =B18+C18+D18 -> 1668.4625
A19: 2000 | B19: =A19*('Costos IA'!$D$6+'Costos IA'!$D$7+'Costos IA'!$D$8+'Costos IA'!$D$9)/'Costos IA'!$D$4 -> 2115.305 | C19: ='Costos IA'!$D$10+'Costos IA'!$D$11 -> 10.53375 | D19: ='Infra Railway'!$H$15 -> 71.45 | E19: =B19+C19+D19 -> 2197.2888
A21: C. Mensajes de chat por persona activa / mes
A22: Mensajes / persona | B22: Costo chat / mes | C22: Resto IA | D22: Infraestructura | E22: TOTAL
A23: 0 | B23: =A23*'Costos IA'!$D$15*(Supuestos!$C$11*Supuestos!$C$21+Supuestos!$C$12*Supuestos!$C$22)/1000000 -> 0 | C23: ='Costos IA'!$D$6+'Costos IA'!$D$7+'Costos IA'!$D$8+'Costos IA'!$D$9+'Costos IA'!$D$11 -> 793.33312 | D23: ='Infra Railway'!$H$15 -> 71.45 | E23: =B23+C23+D23 -> 864.78313
A24: 12 | B24: =A24*'Costos IA'!$D$15*(Supuestos!$C$11*Supuestos!$C$21+Supuestos!$C$12*Supuestos!$C$22)/1000000 -> 10.44 | C24: ='Costos IA'!$D$6+'Costos IA'!$D$7+'Costos IA'!$D$8+'Costos IA'!$D$9+'Costos IA'!$D$11 -> 793.33312 | D24: ='Infra Railway'!$H$15 -> 71.45 | E24: =B24+C24+D24 -> 875.22312
A25: 30 | B25: =A25*'Costos IA'!$D$15*(Supuestos!$C$11*Supuestos!$C$21+Supuestos!$C$12*Supuestos!$C$22)/1000000 -> 26.1 | C25: ='Costos IA'!$D$6+'Costos IA'!$D$7+'Costos IA'!$D$8+'Costos IA'!$D$9+'Costos IA'!$D$11 -> 793.33312 | D25: ='Infra Railway'!$H$15 -> 71.45 | E25: =B25+C25+D25 -> 890.88312
A26: 60 | B26: =A26*'Costos IA'!$D$15*(Supuestos!$C$11*Supuestos!$C$21+Supuestos!$C$12*Supuestos!$C$22)/1000000 -> 52.2 | C26: ='Costos IA'!$D$6+'Costos IA'!$D$7+'Costos IA'!$D$8+'Costos IA'!$D$9+'Costos IA'!$D$11 -> 793.33312 | D26: ='Infra Railway'!$H$15 -> 71.45 | E26: =B26+C26+D26 -> 916.98312
A28: D. Precio unitario YouCam (22 unidades × 750 escaneos)
A29: Modalidad | B29: USD / unidad | C29: USD / mes | D29: Diferencia
A30: Suscripción 10.000+ unidades | B30: 0.046 | C30: =B30*22*'Costos IA'!$D$4 -> 759 | D30: =C30-$C$31 -> -33
A31: Suscripción 500+ unidades | B31: 0.048 | C31: =B31*22*'Costos IA'!$D$4 -> 792 | D31: =C31-$C$31 -> 0
A32: Pay-as-you-go | B32: 0.055 | C32: =B32*22*'Costos IA'!$D$4 -> 907.5 | D32: =C32-$C$31 -> 115.5

Sheet Fuentes
A1: Fuentes, evidencia y límites del modelo
A2: Precios consultados el 25-oct-2026. Los precios de nube y de API cambian: revalidar antes de decidir.
A3: Tema | B3: Referencia | C3: Qué aporta
A4: Railway · precios | B4: https://railway.com/pricing | C4: CPU USD 20/vCPU-mes, RAM USD 10/GB-mes, volumen USD 0,15/GB-mes, egress USD 0,05/GB, Pro USD 20 con USD 20 de uso incluido.
A5: YouCam API · precios | B5: https://yce.perfectcorp.com/ai-api/api-pricing | C5: Suscripción USD 0,048/unidad (500+), PAYG USD 0,055. 13–16 concerns: 22 unidades en HD.
A6: Gemini API · precios | B6: https://ai.google.dev/gemini-api/docs/pricing | C6: Gemini 3.1 Flash-Lite: USD 0,125 / 1M entrada y USD 0,75 / 1M salida (hasta 31-dic-2026).
A7: DeepSeek API · precios | B7: https://api-docs.deepseek.com/quick_start/pricing | C7: deepseek-flash: USD 0,30 / 1M entrada y USD 1,20 / 1M salida en hora pico; mitad en off-peak.
A8: TRM Colombia | B8: https://www.larepublica.co/indicadores-economicos/mercado-cambiario/dolar | C8: TRM 24–26 oct 2026: $3.158,43 COP/USD (fuente Superfinanciera).
A9: Topología Railway | B9: railway.yml | C9: Servicios pgvector-db, redis, ai-worker, backend + entorno staging clonado.
A10: Escaneo facial | B10: backend/src/services/biometric/orchestrator.js | C10: Orden real: YouCam (rostro) + Gemini (manos) + DeepSeek (recomendación y VTO).
A11: 16 acciones HD | B11: backend/src/services/biometric/youcam.client.js | C11: SKIN_ANALYSIS_ACTIONS: 16 acciones HD, HD y SD no se mezclan.
A12: Chat con RAG | B12: backend/src/config/ragConfig.js | C12: topK = 5 documentos por consulta; contexto de servicios cacheado.
A13: Afirmación a contrastar | B13: GIA-14-I-REAL-COST.md | C13: Estima USD 0,04/persona/mes (YouCam 2 llamadas ≈ USD 0,02). No cuadra con 22 unidades por escaneo.
A16: Límites
A17: No incluye impuestos, comisiones de pasarela de pago, Firebase/Google Analytics, correo transaccional, builds de CI, egreso de video ni costos de soporte. Los promedios de vCPU/RAM de Railway son supuestos de dimensionamiento: reemplácelos por las métricas reales del dashboard para convertir esta simulación en un pronóstico.
